{
	"credit": "Made with Blockbench",
	"parent": "block/block",
	"textures": {
		"0": "conquest:block/1_basic_refined/3_wood/tarred_oak_wood_beam",
		"1": "conquest:block/1_basic_refined/3_wood/tarred_oak_wood_beam_top",
		"particle": "conquest:block/1_basic_refined/3_wood/tarred_oak_wood_beam"
	},
	"elements": [
		{
			"name": "Cube",
			"from": [6.025, 16, 6.025],
			"to": [9.975, 26, 9.975],
			"faces": {
				"north": {"uv": [0, 6, 3.95, 16], "texture": "#0"},
				"east": {"uv": [12, 6, 15.95, 16], "texture": "#0"},
				"south": {"uv": [0, 6, 3.95, 16], "texture": "#0"},
				"west": {"uv": [12, 6, 15.95, 16], "texture": "#0"},
				"up": {"uv": [6, 5.5, 9.95, 9.45], "texture": "#1"},
				"down": {"uv": [11, 4, 14.95, 7.95], "texture": "#0"}
			}
		},
		{
			"name": "Cube",
			"from": [6, 0, 6],
			"to": [10, 16, 10],
			"faces": {
				"north": {"uv": [0, 0, 4, 16], "texture": "#0"},
				"east": {"uv": [12, 0, 16, 16], "texture": "#0"},
				"south": {"uv": [0, 0, 4, 16], "texture": "#0"},
				"west": {"uv": [12, 0, 16, 16], "texture": "#0"},
				"up": {"uv": [9.5, 6.5, 13.5, 10.5], "texture": "#0"},
				"down": {"uv": [5.5, 6, 9.5, 10], "texture": "#1"}
			}
		}
	],
	"groups": [0,
		{
			"name": "rustic_fence_post",
			"origin": [8, 8, 8],
			"children": [1]
		}
	]
}