{
	"credit": "Made with Blockbench",
	"textures": {
		"0": "conquest:block/2_advanced_refined/2_metal/steel_beam",
		"particle": "conquest:block/2_advanced_refined/2_metal/steel_beam"
	},
	"elements": [
		{
			"from": [5.0039, 6.11639, 5.85139],
			"to": [11.00391, 21.3117, 9.85139],
			"rotation": {"angle": -45, "axis": "x", "origin": [8.01953, 8.46014, 7.85139]},
			"faces": {
				"north": {"uv": [0, 0, 6.00001, 15.19531], "texture": "#0"},
				"east": {"uv": [6, 0, 10, 15.19531], "texture": "#0"},
				"south": {"uv": [0, 0, 6.00001, 15.19531], "texture": "#0"},
				"west": {"uv": [6, 0, 10, 15.19531], "texture": "#0"},
				"up": {"uv": [10, 0, 14, 6.00001], "rotation": 90, "texture": "#0"},
				"down": {"uv": [10, 0, 14, 6.00001], "rotation": 90, "texture": "#0"}
			}
		},
		{
			"from": [5.01172, 7.25736, 3.6408],
			"to": [10.96485, 22.61283, 7.6408],
			"rotation": {"angle": 45, "axis": "x", "origin": [8.01172, 5.75736, 5.6408]},
			"faces": {
				"north": {"uv": [0, 0, 5.95313, 15.35547], "texture": "#0"},
				"east": {"uv": [6, 0, 10, 15.35547], "texture": "#0"},
				"south": {"uv": [0, 0, 5.95313, 15.35547], "texture": "#0"},
				"west": {"uv": [6, 0, 10, 15.35547], "texture": "#0"},
				"up": {"uv": [10, 0, 14, 5.95313], "rotation": 90, "texture": "#0"},
				"down": {"uv": [10, 0, 14, 5.95313], "rotation": 90, "texture": "#0"}
			}
		}
	],
	"display": {
		"gui": {
			"rotation": [30, 135, 0],
			"scale": [0.6, 0.6, 0.6]
		}
	},
	"groups": [
		{
			"name": "sidewaycross",
			"origin": [8.19542, 8.21014, 7.75],
			"children": [0, 1]
		}
	]
}